Workbook

Sheet P&L Statement
A1: Dealership Profit & Loss Statement | D1: Revenue | E1: COGS | F1: Gross Profit | G1: Opex | H1: Net Profit
D2: =B7 -> 0 | E2: =B10 -> 0 | F2: =B12 -> 0 | G2: =B22 -> 0 | H2: =B24 -> 0
A3: Period Start | B3: 46023
A4: Period End | B4: 46387
A6: REVENUE
A7: Total Revenue | B7: =SUMIFS('Sales Log'!$G$2:$G$302,'Sales Log'!$A$2:$A$302,">="&B3,'Sales Log'!$A$2:$A$302,"<="&B4) -> 0
A9: COST OF GOODS SOLD
A10: Total COGS | B10: =SUMIFS('Sales Log'!$H$2:$H$302,'Sales Log'!$A$2:$A$302,">="&B3,'Sales Log'!$A$2:$A$302,"<="&B4) -> 0
A12: GROSS PROFIT | B12: =B7-B10 -> 0
A13: Gross Margin % | B13: =IFERROR(B12/B7,0) -> 0
A15: OPERATING EXPENSES
A16: Salaries & Commissions | B16: 0
A17: Rent & Facilities | B17: 0
A18: Marketing & Advertising | B18: 0
A19: Utilities | B19: 0
A20: Insurance | B20: 0
A21: Other Operating Expenses | B21: 0
A22: TOTAL OPERATING EXPENSES | B22: =SUM(B16:B21) -> 0
A24: NET PROFIT | B24: =B12-B22 -> 0
A25: Net Margin % | B25: =IFERROR(B24/B7,0) -> 0
A28: Legend: yellow = your input (period dates, operating expense amounts per period). Black = calculated automatically from the Sales Log sheet -- log every sale there first. Revenue/COGS totals only include Sales Log rows whose Sale Date falls within Period Start/End above.

Sheet Sales Log
A1: Sale Date | B1: Model Name | C1: Units Sold | D1: Sale Price/Unit (USD) | E1: MSRP (Ref.) | F1: Est. Unit Cost (Ref.) | G1: Revenue | H1: COGS | I1: Gross Profit | J1: Salesperson
A2: 2023-10-05 | B2: GLC 350e 4MATIC SUV | C2: 3 | D2: 59900 | E2: 59900 | F2: =IFERROR(INDEX('Model Pricing'!$O$2:$O$52,MATCH(B2,'Model Pricing'!$A$2:$A$52,0)),"") -> 52712 | G2: =IFERROR(C2*D2,"") -> 179700 | H2: =IFERROR(C2*F2,"") -> 158136 | I2: =IFERROR(G2-H2,"") -> 21564
A3: 2026-08-28 | B3: E 350 Sedan | C3: 2 | D3: 53760 | E3: =IFERROR(INDEX('Model Pricing'!$E$2:$E$52,MATCH(B3,'Model Pricing'!$A$2:$A$52,0)),"") -> 65200 | F3: =IFERROR(INDEX('Model Pricing'!$O$2:$O$52,MATCH(B3,'Model Pricing'!$A$2:$A$52,0)),"") -> 57376 | G3: =IFERROR(C3*D3,"") -> 107520 | H3: =IFERROR(C3*F3,"") -> 114752 | I3: =IFERROR(G3-H3,"") -> -7232
A4: 2026-08-28 | B4: E 350 Sedan | C4: 2 | D4: 53760 | E4: =IFERROR(INDEX('Model Pricing'!$E$2:$E$52,MATCH(B4,'Model Pricing'!$A$2:$A$52,0)),"") -> 65200 | F4: =IFERROR(INDEX('Model Pricing'!$O$2:$O$52,MATCH(B4,'Model Pricing'!$A$2:$A$52,0)),"") -> 57376 | G4: =IFERROR(C4*D4,"") -> 107520 | H4: =IFERROR(C4*F4,"") -> 114752 | I4: =IFERROR(G4-H4,"") -> -7232
E5: =IFERROR(INDEX('Model Pricing'!$E$2:$E$52,MATCH(B5,'Model Pricing'!$A$2:$A$52,0)),"") | F5: =IFERROR(INDEX('Model Pricing'!$O$2:$O$52,MATCH(B5,'Model Pricing'!$A$2:$A$52,0)),"") | G5: =IFERROR(C5*D5,"") -> 0 | H5: =IFERROR(C5*F5,"") | I5: =IFERROR(G5-H5,"")
E6: =IFERROR(INDEX('Model Pricing'!$E$2:$E$52,MATCH(B6,'Model Pricing'!$A$2:$A$52,0)),"") | F6: =IFERROR(INDEX('Model Pricing'!$O$2:$O$52,MATCH(B6,'Model Pricing'!$A$2:$A$52,0)),"") | G6: =IFERROR(C6*D6,"") -> 0 | H6: =IFERROR(C6*F6,"") | I6: =IFERROR(G6-H6,"")
E7: =IFERROR(INDEX('Model Pricing'!$E$2:$E$52,MATCH(B7,'Model Pricing'!$A$2:$A$52,0)),"") | F7: =IFERROR(INDEX('Model Pricing'!$O$2:$O$52,MATCH(B7,'Model Pricing'!$A$2:$A$52,0)),"") | G7: =IFERROR(C7*D7,"") -> 0 | H7: =IFERROR(C7*F7,"") | I7: =IFERROR(G7-H7,"")
E8: =IFERROR(INDEX('Model Pricing'!$E$2:$E$52,MATCH(B8,'Model Pricing'!$A$2:$A$52,0)),"") | F8: =IFERROR(INDEX('Model Pricing'!$O$2:$O$52,MATCH(B8,'Model Pricing'!$A$2:$A$52,0)),"") | G8: =IFERROR(C8*D8,"") -> 0 | H8: =IFERROR(C8*F8,"") | I8: =IFERROR(G8-H8,"")
E9: =IFERROR(INDEX('Model Pricing'!$E$2:$E$52,MATCH(B9,'Model Pricing'!$A$2:$A$52,0)),"") | F9: =IFERROR(INDEX('Model Pricing'!$O$2:$O$52,MATCH(B9,'Model Pricing'!$A$2:$A$52,0)),"") | G9: =IFERROR(C9*D9,"") -> 0 | H9: =IFERROR(C9*F9,"") | I9: =IFERROR(G9-H9,"")
E10: =IFERROR(INDEX('Model Pricing'!$E$2:$E$52,MATCH(B10,'Model Pricing'!$A$2:$A$52,0)),"") | F10: =IFERROR(INDEX('Model Pricing'!$O$2:$O$52,MATCH(B10,'Model Pricing'!$A$2:$A$52,0)),"") | G10: =IFERROR(C10*D10,"") -> 0 | H10: =IFERROR(C10*F10,"") | I10: =IFERROR(G10-H10,"")
E11: =IFERROR(INDEX('Model Pricing'!$E$2:$E$52,MATCH(B11,'Model Pricing'!$A$2:$A$52,0)),"") | F11: =IFERROR(INDEX('Model Pricing'!$O$2:$O$52,MATCH(B11,'Model Pricing'!$A$2:$A$52,0)),"") | G11: =IFERROR(C11*D11,"") -> 0 | H11: =IFERROR(C11*F11,"") | I11: =IFERROR(G11-H11,"")
E12: =IFERROR(INDEX('Model Pricing'!$E$2:$E$52,MATCH(B12,'Model Pricing'!$A$2:$A$52,0)),"") | F12: =IFERROR(INDEX('Model Pricing'!$O$2:$O$52,MATCH(B12,'Model Pricing'!$A$2:$A$52,0)),"") | G12: =IFERROR(C12*D12,"") -> 0 | H12: =IFERROR(C12*F12,"") | I12: =IFERROR(G12-H12,"")
E13: =IFERROR(INDEX('Model Pricing'!$E$2:$E$52,MATCH(B13,'Model Pricing'!$A$2:$A$52,0)),"") | F13: =IFERROR(INDEX('Model Pricing'!$O$2:$O$52,MATCH(B13,'Model Pricing'!$A$2:$A$52,0)),"") | G13: =IFERROR(C13*D13,"") -> 0 | H13: =IFERROR(C13*F13,"") | I13: =IFERROR(G13-H13,"")
E14: =IFERROR(INDEX('Model Pricing'!$E$2:$E$52,MATCH(B14,'Model Pricing'!$A$2:$A$52,0)),"") | F14: =IFERROR(INDEX('Model Pricing'!$O$2:$O$52,MATCH(B14,'Model Pricing'!$A$2:$A$52,0)),"") | G14: =IFERROR(C14*D14,"") -> 0 | H14: =IFERROR(C14*F14,"") | I14: =IFERROR(G14-H14,"")
E15: =IFERROR(INDEX('Model Pricing'!$E$2:$E$52,MATCH(B15,'Model Pricing'!$A$2:$A$52,0)),"") | F15: =IFERROR(INDEX('Model Pricing'!$O$2:$O$52,MATCH(B15,'Model Pricing'!$A$2:$A$52,0)),"") | G15: =IFERROR(C15*D15,"") -> 0 | H15: =IFERROR(C15*F15,"") | I15: =IFERROR(G15-H15,"")
E16: =IFERROR(INDEX('Model Pricing'!$E$2:$E$52,MATCH(B16,'Model Pricing'!$A$2:$A$52,0)),"") | F16: =IFERROR(INDEX('Model Pricing'!$O$2:$O$52,MATCH(B16,'Model Pricing'!$A$2:$A$52,0)),"") | G16: =IFERROR(C16*D16,"") -> 0 | H16: =IFERROR(C16*F16,"") | I16: =IFERROR(G16-H16,"")
... E302: =IFERROR(INDEX('Model Pricing'!$E$2:$E$52,MATCH(B302,'Model Pricing'!$A$2:$A$52,0)),"") | F302: =IFERROR(INDEX('Model Pricing'!$O$2:$O$52,MATCH(B302,'Model Pricing'!$A$2:$A$52,0)),"") | G302: =IFERROR(C302*D302,"") -> 0 | H302: =IFERROR(C302*F302,"") | I302: =IFERROR(G302-H302,"")
A305: Legend: blue = your input (date, model, units, price, salesperson). Black = calculated automatically from Model Pricing sheet. Pick Model Name from the dropdown so MSRP/cost lookups resolve correctly.
A306: 2026-03-15 | B306: GLC 300 SUV | C306: 2 | D306: 52000 | G306: 104000
A307: 2023-10-15 | B307: GLC 300 SUV | C307: 2 | D307: 52000

Sheet Inventory
A1: Model Name | B1: Units in Stock | C1: Est. Unit Cost (Ref.) | D1: Total Inventory Value | E1: Reorder Level | F1: Status
A2: ='Model Pricing'!A2 -> C 300 Sedan | B2: 0 | C2: ='Model Pricing'!O2 -> 43692 | D2: =B2*C2 -> 0 | E2: 2 | F2: =IF(B2<=E2,"Reorder","OK") -> Reorder
A3: ='Model Pricing'!A3 -> C 300 4MATIC Sedan | B3: 0 | C3: ='Model Pricing'!O3 -> 45452 | D3: =B3*C3 -> 0 | E3: 2 | F3: =IF(B3<=E3,"Reorder","OK") -> Reorder
A4: ='Model Pricing'!A4 -> AMG C 43 Sedan | B4: 0 | C4: ='Model Pricing'!O4 -> 56452 | D4: =B4*C4 -> 0 | E4: 2 | F4: =IF(B4<=E4,"Reorder","OK") -> Reorder
A5: ='Model Pricing'!A5 -> AMG C 63 S E PERFORMANCE Sedan | B5: 0 | C5: ='Model Pricing'!O5 -> 77440 | D5: =B5*C5 -> 0 | E5: 2 | F5: =IF(B5<=E5,"Reorder","OK") -> Reorder
A6: ='Model Pricing'!A6 -> E 350 Sedan | B6: 0 | C6: ='Model Pricing'!O6 -> 57376 | D6: =B6*C6 -> 0 | E6: 2 | F6: =IF(B6<=E6,"Reorder","OK") -> Reorder
A7: ='Model Pricing'!A7 -> E 350 4MATIC Sedan | B7: 0 | C7: ='Model Pricing'!O7 -> 59576 | D7: =B7*C7 -> 0 | E7: 2 | F7: =IF(B7<=E7,"Reorder","OK") -> Reorder
A8: ='Model Pricing'!A8 -> E 450 4MATIC Sedan | B8: 0 | C8: ='Model Pricing'!O8 -> 64856 | D8: =B8*C8 -> 0 | E8: 2 | F8: =IF(B8<=E8,"Reorder","OK") -> Reorder
A9: ='Model Pricing'!A9 -> AMG E 53 HYBRID Sedan | B9: 0 | C9: ='Model Pricing'!O9 -> 80168 | D9: =B9*C9 -> 0 | E9: 2 | F9: =IF(B9<=E9,"Reorder","OK") -> Reorder
A10: ='Model Pricing'!A10 -> S 500 4MATIC Sedan | B10: 0 | C10: ='Model Pricing'!O10 -> 103224 | D10: =B10*C10 -> 0 | E10: 2 | F10: =IF(B10<=E10,"Reorder","OK") -> Reorder
A11: ='Model Pricing'!A11 -> S 580 4MATIC Sedan | B11: 0 | C11: ='Model Pricing'!O11 -> 112772 | D11: =B11*C11 -> 0 | E11: 2 | F11: =IF(B11<=E11,"Reorder","OK") -> Reorder
A12: ='Model Pricing'!A12 -> S 580e 4MATIC Sedan | B12: 0 | C12: ='Model Pricing'!O12 -> 112420 | D12: =B12*C12 -> 0 | E12: 2 | F12: =IF(B12<=E12,"Reorder","OK") -> Reorder
A13: ='Model Pricing'!A13 -> Maybach S 580 4MATIC | B13: 0 | C13: ='Model Pricing'!O13 -> 174504 | D13: =B13*C13 -> 0 | E13: 2 | F13: =IF(B13<=E13,"Reorder","OK") -> Reorder
... A52: ='Model Pricing'!A52 -> AMG SL 63 Roadster | B52: 0 | C52: ='Model Pricing'!O52 -> 161040 | D52: =B52*C52 -> 0 | E52: 2 | F52: =IF(B52<=E52,"Reorder","OK") -> Reorder
A53: TOTAL | D53: =SUM(D2:D52) -> 0
A55: Legend: blue = your input (Units in Stock, Reorder Level). Black = calculated. Est. Unit Cost pulls from the same assumption cell as Model Pricing (cell O1 there).

Sheet Model Pricing
A1: Model Name | B1: Class / Lineup | C1: Vehicle Type | D1: Sub-Brand / Series | E1: Base MSRP (USD) | F1: Drivetrain | G1: Fuel Type / Powertrain | H1: Engine Details | I1: Horsepower (hp) | J1: Torque (lb-ft) | K1: Transmission | L1: 0-60 mph (sec) | M1: Est. Fuel Economy / Range | N1: Seating Capacity | O1: Est. Dealer Cost (USD) | P1: 0.88
A2: C 300 Sedan | B2: C-Class | C2: Sedan | D2: Core / Luxury | E2: 49650 | F2: RWD | G2: Gasoline Mild-Hybrid | H2: 2.0L Inline-4 Turbo | I2: 255 hp | J2: 295 lb-ft | K2: 9G-TRONIC 9-Speed Automatic | L2: 6.0 sec | M2: 26 MPG City / 36 MPG Hwy | N2: 5 | O2: =E2*$P$1 -> 43692 | P2: Dealer Cost % of MSRP
A3: C 300 4MATIC Sedan | B3: C-Class | C3: Sedan | D3: Core / Luxury | E3: 51650 | F3: AWD (4MATIC) | G3: Gasoline Mild-Hybrid | H3: 2.0L Inline-4 Turbo | I3: 255 hp | J3: 295 lb-ft | K3: 9G-TRONIC 9-Speed Automatic | L3: 6.0 sec | M3: 23 MPG City / 33 MPG Hwy | N3: 5 | O3: =E3*$P$1 -> 45452
A4: AMG C 43 Sedan | B4: C-Class | C4: Sedan | D4: Mercedes-AMG | E4: 64150 | F4: AWD (AMG Performance 4MATIC+) | G4: Gasoline Mild-Hybrid | H4: 2.0L Inline-4 Turbo w/ Electric Exhaust-Gas Turbo | I4: 402 hp | J4: 369 lb-ft | K4: AMG SPEEDSHIFT MCT 9-Speed | L4: 4.6 sec | M4: 20 MPG City / 28 MPG Hwy | N4: 5 | O4: =E4*$P$1 -> 56452
A5: AMG C 63 S E PERFORMANCE Sedan | B5: C-Class | C5: Sedan | D5: Mercedes-AMG | E5: 88000 | F5: AWD (AMG Performance 4MATIC+) | G5: Plug-in Hybrid (PHEV) | H5: 2.0L Inline-4 Turbo + Rear Electric Motor | I5: 671 hp | J5: 752 lb-ft | K5: AMG SPEEDSHIFT MCT 9-Speed | L5: 3.3 sec | M5: 41 MPGe / 21 MPG Combined | N5: 5 | O5: =E5*$P$1 -> 77440
A6: E 350 Sedan | B6: E-Class | C6: Sedan | D6: Core / Luxury | E6: 65200 | F6: RWD | G6: Gasoline Mild-Hybrid | H6: 2.0L Inline-4 Turbo | I6: 255 hp | J6: 295 lb-ft | K6: 9G-TRONIC 9-Speed Automatic | L6: 6.1 sec | M6: 24 MPG City / 33 MPG Hwy | N6: 5 | O6: =E6*$P$1 -> 57376
A7: E 350 4MATIC Sedan | B7: E-Class | C7: Sedan | D7: Core / Luxury | E7: 67700 | F7: AWD (4MATIC) | G7: Gasoline Mild-Hybrid | H7: 2.0L Inline-4 Turbo | I7: 255 hp | J7: 295 lb-ft | K7: 9G-TRONIC 9-Speed Automatic | L7: 6.1 sec | M7: 24 MPG City / 33 MPG Hwy | N7: 5 | O7: =E7*$P$1 -> 59576
A8: E 450 4MATIC Sedan | B8: E-Class | C8: Sedan | D8: Core / Luxury | E8: 73700 | F8: AWD (4MATIC) | G8: Gasoline Mild-Hybrid | H8: 3.0L Inline-6 Turbo | I8: 375 hp | J8: 369 lb-ft | K8: 9G-TRONIC 9-Speed Automatic | L8: 4.4 sec | M8: 22 MPG City / 31 MPG Hwy | N8: 5 | O8: =E8*$P$1 -> 64856
A9: AMG E 53 HYBRID Sedan | B9: E-Class | C9: Sedan | D9: Mercedes-AMG | E9: 91100 | F9: AWD (AMG Performance 4MATIC+) | G9: Plug-in Hybrid (PHEV) | H9: 3.0L Inline-6 Turbo + Electric Motor | I9: 577 hp | J9: 553 lb-ft | K9: AMG SPEEDSHIFT TCT 9-Speed | L9: 3.7 sec | M9: 54 MPGe est. | N9: 5 | O9: =E9*$P$1 -> 80168
A10: S 500 4MATIC Sedan | B10: S-Class | C10: Flagship Sedan | D10: Core / Luxury | E10: 117300 | F10: AWD (4MATIC) | G10: Gasoline Mild-Hybrid | H10: 3.0L Inline-6 Turbo | I10: 442 hp | J10: 413 lb-ft | K10: 9G-TRONIC 9-Speed Automatic | L10: 4.5 sec | M10: 21 MPG City / 31 MPG Hwy | N10: 5 | O10: =E10*$P$1 -> 103224
A11: S 580 4MATIC Sedan | B11: S-Class | C11: Flagship Sedan | D11: Core / Luxury | E11: 128150 | F11: AWD (4MATIC) | G11: Gasoline Mild-Hybrid | H11: 4.0L V8 Biturbo | I11: 496 hp | J11: 516 lb-ft | K11: 9G-TRONIC 9-Speed Automatic | L11: 4.3 sec | M11: 18 MPG City / 27 MPG Hwy | N11: 5 | O11: =E11*$P$1 -> 112772
A12: S 580e 4MATIC Sedan | B12: S-Class | C12: Flagship Sedan | D12: Core / Luxury | E12: 127750 | F12: AWD (4MATIC) | G12: Plug-in Hybrid (PHEV) | H12: 3.0L Inline-6 Turbo + Electric Motor | I12: 510 hp | J12: 516 lb-ft | K12: 9G-TRONIC 9-Speed Automatic | L12: 4.8 sec | M12: 46 Miles Electric Range | N12: 5 | O12: =E12*$P$1 -> 112420
A13: Maybach S 580 4MATIC | B13: S-Class / Maybach | C13: Ultra-Luxury Sedan | D13: Mercedes-Maybach | E13: 198300 | F13: AWD (4MATIC) | G13: Gasoline Mild-Hybrid | H13: 4.0L V8 Biturbo | I13: 496 hp | J13: 516 lb-ft | K13: 9G-TRONIC 9-Speed Automatic | L13: 4.7 sec | M13: 15 MPG City / 25 MPG Hwy | N13: 4 | O13: =E13*$P$1 -> 174504
A14: Maybach S 680 4MATIC | B14: S-Class / Maybach | C14: Ultra-Luxury Sedan | D14: Mercedes-Maybach | E14: 235000 | F14: AWD (4MATIC) | G14: Gasoline | H14: 6.0L V12 Biturbo | I14: 621 hp | J14: 664 lb-ft | K14: 9G-TRONIC 9-Speed Automatic | L14: 4.4 sec | M14: 12 MPG City / 20 MPG Hwy | N14: 4 | O14: =E14*$P$1 -> 206800
... A52: AMG SL 63 Roadster | B52: SL-Class | C52: Roadster Convertible | D52: Mercedes-AMG | E52: 183000 | F52: AWD (AMG Performance 4MATIC+) | G52: Gasoline | H52: 4.0L V8 Biturbo | I52: 577 hp | J52: 590 lb-ft | K52: AMG SPEEDSHIFT MCT 9-Speed | L52: 3.5 sec | M52: 14 MPG City / 21 MPG Hwy | N52: 4 | O52: =E52*$P$1 -> 161040
